{
  "type": "fusion:connecting",
  "parent": "minecraft:block/cube",
  "connections": [
    {
      "type": "fusion:is_same_state"
    }
  ],
  "loader": "fusion:model",
  "textures": {
    "down": "rechiseledcreate:block/dark_oak_window_slim_end",
    "east": "rechiseledcreate:block/dark_oak_window_slim_side",
    "north": "rechiseledcreate:block/dark_oak_window_slim_side",
    "particle": "rechiseledcreate:block/dark_oak_window_slim_side",
    "south": "rechiseledcreate:block/dark_oak_window_slim_side",
    "up": "rechiseledcreate:block/dark_oak_window_slim_end",
    "west": "rechiseledcreate:block/dark_oak_window_slim_side"
  }
}